[
    {
        "Id": 1,
        "Text": "Как называется ближайшая к Земле звезда?",
        "Answer": "Солнце",
        "AcceptableAnswers": "Солнце"
    },
    {
        "Id": 2,
        "Text": "В какой стране находится Эйфелева башня?",
        "Answer": "Франция",
        "AcceptableAnswers": "Франция"
    },
    {
        "Id": 3,
        "Text": "Сколько месяцев в году имеют 28 дней?",
        "Answer": "Все",
        "AcceptableAnswers": "Все 12, 12"
    },
    {
        "Id": 4,
        "Text": "Как называется столица России?",
        "Answer": "Москва",
        "AcceptableAnswers": "Москва"
    },
    {
        "Id": 5,
        "Text": "Какой химический элемент обозначается символом O?",
        "Answer": "Кислород",
        "AcceptableAnswers": "Кислород"
    },
    {
        "Id": 6,
        "Text": "Как звали первого космонавта планеты?",
        "Answer": "Юрий Гагарин",
        "AcceptableAnswers": "Гагарин"
    },
    {
        "Id": 7,
        "Text": "Сколько у человека легких?",
        "Answer": "Два",
        "AcceptableAnswers": "2, пара"
    },
    {
        "Id": 8,
        "Text": "На каком континенте находится река Амазонка?",
        "Answer": "Южная Америка",
        "AcceptableAnswers": "Южная Америка"
    },
    {
        "Id": 9,
        "Text": "В каком виде спорта используется рапира?",
        "Answer": "Фехтование",
        "AcceptableAnswers": "Фехтование"
    },
    {
        "Id": 10,
        "Text": "Как называется замерзшая вода?",
        "Answer": "Лед",
        "AcceptableAnswers": "Лед"
    },
    {
        "Id": 11,
        "Text": "Какой цвет получится при смешивании синего и красного?",
        "Answer": "Фиолетовый",
        "AcceptableAnswers": "Фиолетовый"
    },
    {
        "Id": 12,
        "Text": "Как называется столица Великобритании?",
        "Answer": "Лондон",
        "AcceptableAnswers": "Лондон"
    },
    {
        "Id": 13,
        "Text": "Сколько секунд в одной минуте?",
        "Answer": "60",
        "AcceptableAnswers": "Шестьдесят"
    },
    {
        "Id": 14,
        "Text": "Как называется самая высокая гора в мире?",
        "Answer": "Эверест",
        "AcceptableAnswers": "Джомолунгма"
    },
    {
        "Id": 15,
        "Text": "Какой океан самый большой на Земле?",
        "Answer": "Тихий",
        "AcceptableAnswers": "Тихий"
    },
    {
        "Id": 16,
        "Text": "В каком месяце начинается календарная осень?",
        "Answer": "Сентябрь",
        "AcceptableAnswers": "Сентябрь"
    },
    {
        "Id": 17,
        "Text": "Сколько ног у паука?",
        "Answer": "Восемь",
        "AcceptableAnswers": "8"
    },
    {
        "Id": 18,
        "Text": "Как называется столица Италии?",
        "Answer": "Рим",
        "AcceptableAnswers": "Рим"
    },
    {
        "Id": 19,
        "Text": "Какая планета называется «Красной»?",
        "Answer": "Марс",
        "AcceptableAnswers": "Марс"
    },
    {
        "Id": 20,
        "Text": "Как называется сказка про деревянного мальчика с длинным носом?",
        "Answer": "Буратино",
        "AcceptableAnswers": "Пиноккио"
    },
    {
        "Id": 21,
        "Text": "Какой инструмент используют для измерения температуры?",
        "Answer": "Термометр",
        "AcceptableAnswers": "Градусник"
    },
    {
        "Id": 22,
        "Text": "Сколько цветов в радуге?",
        "Answer": "Семь",
        "AcceptableAnswers": "7"
    },
    {
        "Id": 23,
        "Text": "Как называется детеныш овцы?",
        "Answer": "Ягненок",
        "AcceptableAnswers": "Ягненок"
    },
    {
        "Id": 24,
        "Text": "В каком государстве находится город Рим?",
        "Answer": "Италия",
        "AcceptableAnswers": "Италия"
    },
    {
        "Id": 25,
        "Text": "Как называется прибор для определения сторон горизонта?",
        "Answer": "Компас",
        "AcceptableAnswers": "Компас"
    },
    {
        "Id": 26,
        "Text": "Какое животное называют «кораблем пустыни»?",
        "Answer": "Верблюд",
        "AcceptableAnswers": "Верблюд"
    },
    {
        "Id": 27,
        "Text": "Как называется столица Франции?",
        "Answer": "Париж",
        "AcceptableAnswers": "Париж"
    },
    {
        "Id": 28,
        "Text": "На каком языке говорят в Бразилии?",
        "Answer": "Португальский",
        "AcceptableAnswers": "Португальский"
    },
    {
        "Id": 29,
        "Text": "Сколько дней в високосном году?",
        "Answer": "366",
        "AcceptableAnswers": "Триста шестьдесят шесть"
    },
    {
        "Id": 30,
        "Text": "Как называется специалист по изучению звезд?",
        "Answer": "Астроном",
        "AcceptableAnswers": "Астроном"
    },
    {
        "Id": 31,
        "Text": "В каком городе находится Эрмитаж?",
        "Answer": "Санкт-Петербург",
        "AcceptableAnswers": "Питер, Петербург"
    },
    {
        "Id": 32,
        "Text": "Какое вещество занимает большую часть поверхности Земли?",
        "Answer": "Вода",
        "AcceptableAnswers": "Вода"
    },
    {
        "Id": 33,
        "Text": "Как называется самый твердый минерал на Земле?",
        "Answer": "Алмаз",
        "AcceptableAnswers": "Алмаз"
    },
    {
        "Id": 34,
        "Text": "Какая птица считается символом мира?",
        "Answer": "Голубь",
        "AcceptableAnswers": "Голубь"
    },
    {
        "Id": 35,
        "Text": "Сколько копеек в одном рубле?",
        "Answer": "Сто",
        "AcceptableAnswers": "100"
    },
    {
        "Id": 36,
        "Text": "Как называется столица Украины?",
        "Answer": "Киев",
        "AcceptableAnswers": "Киев"
    },
    {
        "Id": 37,
        "Text": "Какое время года следует за летом?",
        "Answer": "Осень",
        "AcceptableAnswers": "Осень"
    },
    {
        "Id": 38,
        "Text": "Какой орган человека качает кровь?",
        "Answer": "Сердце",
        "AcceptableAnswers": "Сердце"
    },
    {
        "Id": 39,
        "Text": "Как называется плод дуба?",
        "Answer": "Желудь",
        "AcceptableAnswers": "Желудь"
    },
    {
        "Id": 40,
        "Text": "В какой стране изобрели бумагу?",
        "Answer": "Китай",
        "AcceptableAnswers": "Китай"
    },
    {
        "Id": 41,
        "Text": "Какое животное является самым быстрым на суше?",
        "Answer": "Гепард",
        "AcceptableAnswers": "Гепард"
    },
    {
        "Id": 42,
        "Text": "Как называется столица Германии?",
        "Answer": "Берлин",
        "AcceptableAnswers": "Берлин"
    },
    {
        "Id": 43,
        "Text": "Какая планета находится ближе всех к Солнцу?",
        "Answer": "Меркурий",
        "AcceptableAnswers": "Меркурий"
    },
    {
        "Id": 44,
        "Text": "Сколько сторон у квадрата?",
        "Answer": "Четыре",
        "AcceptableAnswers": "4"
    },
    {
        "Id": 45,
        "Text": "Как называется жилище медведя в лесу?",
        "Answer": "Берлога",
        "AcceptableAnswers": "Берлога"
    },
    {
        "Id": 46,
        "Text": "В каком океане находится остров Мадагаскар?",
        "Answer": "Индийский",
        "AcceptableAnswers": "Индийский"
    },
    {
        "Id": 47,
        "Text": "Как звали великого русского поэта с фамилией Пушкин?",
        "Answer": "Александр",
        "AcceptableAnswers": "Александр Сергеевич"
    },
    {
        "Id": 48,
        "Text": "Как называется результат сложения двух чисел?",
        "Answer": "Сумма",
        "AcceptableAnswers": "Сумма"
    },
    {
        "Id": 49,
        "Text": "Какая денежная единица используется в США?",
        "Answer": "Доллар",
        "AcceptableAnswers": "Доллар"
    },
    {
        "Id": 50,
        "Text": "Какое млекопитающее является самым крупным?",
        "Answer": "Синий кит",
        "AcceptableAnswers": "Кит"
    },
    {
        "Id": 51,
        "Text": "Как называется столица Японии?",
        "Answer": "Токио",
        "AcceptableAnswers": "Токио"
    },
    {
        "Id": 52,
        "Text": "Какой сегодня век?",
        "Answer": "21",
        "AcceptableAnswers": "Двадцать первый"
    },
    {
        "Id": 53,
        "Text": "Сколько игроков в футбольной команде на поле?",
        "Answer": "11",
        "AcceptableAnswers": "Одиннадцать"
    },
    {
        "Id": 54,
        "Text": "Как называется перерыв между выступлениями в театре?",
        "Answer": "Антракт",
        "AcceptableAnswers": "Антракт"
    },
    {
        "Id": 55,
        "Text": "Какое дерево дает березовый сок?",
        "Answer": "Береза",
        "AcceptableAnswers": "Береза"
    },
    {
        "Id": 56,
        "Text": "Как называется главный город области или страны?",
        "Answer": "Столица",
        "AcceptableAnswers": "Столица"
    },
    {
        "Id": 57,
        "Text": "Как называется сумка туриста для ношения на спине?",
        "Answer": "Рюкзак",
        "AcceptableAnswers": "Рюкзак"
    },
    {
        "Id": 58,
        "Text": "Какой цветок является символом Нидерландов?",
        "Answer": "Тюльпан",
        "AcceptableAnswers": "Тюльпан"
    },
    {
        "Id": 59,
        "Text": "Как называется сказка о девочке в красном головном уборе?",
        "Answer": "Красная Шапочка",
        "AcceptableAnswers": "Красная Шапочка"
    },
    {
        "Id": 60,
        "Text": "Какой газ выдыхает человек?",
        "Answer": "Углекислый газ",
        "AcceptableAnswers": "Углекислый"
    },
    {
        "Id": 61,
        "Text": "Как называется место, где хранятся книги?",
        "Answer": "Библиотека",
        "AcceptableAnswers": "Библиотека"
    },
    {
        "Id": 62,
        "Text": "Кто написал музыку к балету «Лебединое озеро»?",
        "Answer": "Чайковский",
        "AcceptableAnswers": "Петр Ильич Чайковский"
    },
    {
        "Id": 63,
        "Text": "Как называется планета, на которой мы живем?",
        "Answer": "Земля",
        "AcceptableAnswers": "Земля"
    },
    {
        "Id": 64,
        "Text": "Сколько углов у треугольника?",
        "Answer": "Три",
        "AcceptableAnswers": "3"
    },
    {
        "Id": 65,
        "Text": "Как называется палочка, которой дирижер управляет оркестром?",
        "Answer": "Дирижерская палочка",
        "AcceptableAnswers": "Палочка"
    },
    {
        "Id": 66,
        "Text": "Какое животное носит своих детей в сумке?",
        "Answer": "Кенгуру",
        "AcceptableAnswers": "Кенгуру"
    },
    {
        "Id": 67,
        "Text": "Как называется напиток, который получают из зерен кофейного дерева?",
        "Answer": "Кофе",
        "AcceptableAnswers": "Кофе"
    },
    {
        "Id": 68,
        "Text": "В какой стране находится Великая Китайская стена?",
        "Answer": "Китай",
        "AcceptableAnswers": "КНР"
    },
    {
        "Id": 69,
        "Text": "Как называется белое полотно на лодке для ловли ветра?",
        "Answer": "Парус",
        "AcceptableAnswers": "Парус"
    },
    {
        "Id": 70,
        "Text": "Какое слово лишнее: яблоко, груша, огурец, банан?",
        "Answer": "Огурец",
        "AcceptableAnswers": "Огурец (овощ)"
    },
    {
        "Id": 71,
        "Text": "Как называется столица Казахстана?",
        "Answer": "Астана",
        "AcceptableAnswers": "Астана"
    },
    {
        "Id": 72,
        "Text": "Какой день недели идет перед субботой?",
        "Answer": "Пятница",
        "AcceptableAnswers": "Пятница"
    },
    {
        "Id": 73,
        "Text": "Сколько часов в сутках?",
        "Answer": "24",
        "AcceptableAnswers": "Двадцать четыре"
    },
    {
        "Id": 74,
        "Text": "Как называется главная площадь Москвы?",
        "Answer": "Красная площадь",
        "AcceptableAnswers": "Красная"
    },
    {
        "Id": 75,
        "Text": "Как называется извергающаяся гора?",
        "Answer": "Вулкан",
        "AcceptableAnswers": "Вулкан"
    },
    {
        "Id": 76,
        "Text": "Какое животное дает молоко?",
        "Answer": "Корова",
        "AcceptableAnswers": "Корова, коза"
    },
    {
        "Id": 77,
        "Text": "Как называется устройство для связи по голосу?",
        "Answer": "Телефон",
        "AcceptableAnswers": "Телефон"
    },
    {
        "Id": 78,
        "Text": "Какой металл жидкий при комнатной температуре?",
        "Answer": "Ртуть",
        "AcceptableAnswers": "Ртуть"
    },
    {
        "Id": 79,
        "Text": "Как называется самая большая пустыня в мире?",
        "Answer": "Сахара",
        "AcceptableAnswers": "Сахара"
    },
    {
        "Id": 80,
        "Text": "Как называется птица, которая не умеет летать и живет в Антарктиде?",
        "Answer": "Пингвин",
        "AcceptableAnswers": "Пингвин"
    },
    {
        "Id": 81,
        "Text": "В каком городе прошли первые современные Олимпийские игры?",
        "Answer": "Афины",
        "AcceptableAnswers": "Афины"
    },
    {
        "Id": 82,
        "Text": "Как называется единица измерения силы тока?",
        "Answer": "Ампер",
        "AcceptableAnswers": "Ампер"
    },
    {
        "Id": 83,
        "Text": "Как звали мастера, создавшего «Давида»?",
        "Answer": "Микеланджело",
        "AcceptableAnswers": "Микеланджело Буонарроти"
    },
    {
        "Id": 84,
        "Text": "Сколько жизней у кошки по легенде?",
        "Answer": "Девять",
        "AcceptableAnswers": "9"
    },
    {
        "Id": 85,
        "Text": "Как называется ягода, из которой делают вино?",
        "Answer": "Виноград",
        "AcceptableAnswers": "Виноград"
    },
    {
        "Id": 86,
        "Text": "Какая река считается самой длинной в мире (согласно новым данным)?",
        "Answer": "Амазонка",
        "AcceptableAnswers": "Амазонка"
    },
    {
        "Id": 87,
        "Text": "Какой фрукт называют «райским»?",
        "Answer": "Яблоко",
        "AcceptableAnswers": "Яблоко"
    },
    {
        "Id": 88,
        "Text": "Как называется столица Испании?",
        "Answer": "Мадрид",
        "AcceptableAnswers": "Мадрид"
    },
    {
        "Id": 89,
        "Text": "Сколько чудес света в классическом списке?",
        "Answer": "Семь",
        "AcceptableAnswers": "7"
    },
    {
        "Id": 90,
        "Text": "Как называется праздник окончания зимы?",
        "Answer": "Масленица",
        "AcceptableAnswers": "Масленица"
    },
    {
        "Id": 91,
        "Text": "Какой химический элемент основной в составе воздуха?",
        "Answer": "Азот",
        "AcceptableAnswers": "Азот"
    },
    {
        "Id": 92,
        "Text": "Как называется столица Беларуси?",
        "Answer": "Минск",
        "AcceptableAnswers": "Минск"
    },
    {
        "Id": 93,
        "Text": "Какой художник нарисовал Мону Лизу?",
        "Answer": "Леонардо да Винчи",
        "AcceptableAnswers": "Леонардо, Да Винчи"
    },
    {
        "Id": 94,
        "Text": "Сколько лет длилась Столетняя война?",
        "Answer": "116 лет",
        "AcceptableAnswers": "116"
    },
    {
        "Id": 95,
        "Text": "Как называется столица Египта?",
        "Answer": "Каир",
        "AcceptableAnswers": "Каир"
    },
    {
        "Id": 96,
        "Text": "Как называется крупнейший остров планеты?",
        "Answer": "Гренландия",
        "AcceptableAnswers": "Гренландия"
    },
    {
        "Id": 97,
        "Text": "Как звали бога грома в скандинавской мифологии?",
        "Answer": "Тор",
        "AcceptableAnswers": "Тор"
    },
    {
        "Id": 98,
        "Text": "Как называется город, в котором родился Иисус Христос?",
        "Answer": "Вифлеем",
        "AcceptableAnswers": "Вифлеем"
    },
    {
        "Id": 99,
        "Text": "Сколько полос на флаге США?",
        "Answer": "13",
        "AcceptableAnswers": "Тринадцать"
    },
    {
        "Id": 100,
        "Text": "Как называется наука о прошлом человечества?",
        "Answer": "История",
        "AcceptableAnswers": "История"
    },
    {
        "Id": 101,
        "Text": "Какой океан омывает восточное побережье США?",
        "Answer": "Атлантический",
        "AcceptableAnswers": "Атлантический"
    },
    {
        "Id": 102,
        "Text": "Как называется столица Австралии?",
        "Answer": "Канберра",
        "AcceptableAnswers": "Канберра"
    },
    {
        "Id": 103,
        "Text": "На каком музыкальном инструменте играл Шерлок Холмс?",
        "Answer": "Скрипка",
        "AcceptableAnswers": "Скрипка"
    },
    {
        "Id": 104,
        "Text": "Как называется самая длинная река в Африке?",
        "Answer": "Нил",
        "AcceptableAnswers": "Нил"
    },
    {
        "Id": 105,
        "Text": "Кто написал роман «Война и мир»?",
        "Answer": "Толстой",
        "AcceptableAnswers": "Толстой"
    },
    {
        "Id": 106,
        "Text": "Как называется детеныш лошади?",
        "Answer": "Жеребенок",
        "AcceptableAnswers": "Жеребенок"
    },
    {
        "Id": 107,
        "Text": "В каком городе находится статуя Свободы?",
        "Answer": "Нью-Йорк",
        "AcceptableAnswers": "Нью-Йорк"
    },
    {
        "Id": 108,
        "Text": "Какой металл самый легкий?",
        "Answer": "Литий",
        "AcceptableAnswers": "Литий"
    },
    {
        "Id": 109,
        "Text": "Какое море омывает берега Египта на востоке?",
        "Answer": "Красное",
        "AcceptableAnswers": "Красное"
    },
    {
        "Id": 110,
        "Text": "В каком году Юрий Гагарин полетел в космос?",
        "Answer": "1961",
        "AcceptableAnswers": "1961"
    },
    {
        "Id": 111,
        "Text": "Как называется самая высокая трава?",
        "Answer": "Бамбук",
        "AcceptableAnswers": "Бамбук"
    },
    {
        "Id": 112,
        "Text": "Кто открыл Америку?",
        "Answer": "Колумб",
        "AcceptableAnswers": "Колумб"
    },
    {
        "Id": 113,
        "Text": "Какой самый твердый карандаш?",
        "Answer": "Т",
        "AcceptableAnswers": "Т"
    },
    {
        "Id": 114,
        "Text": "Как называется место пересечения экватора и нулевого меридиана?",
        "Answer": "Гвинейский залив",
        "AcceptableAnswers": "Гвинейский залив"
    },
    {
        "Id": 115,
        "Text": "Из какого дерева делают спички?",
        "Answer": "Осина",
        "AcceptableAnswers": "Осина"
    },
    {
        "Id": 116,
        "Text": "Как называется группа волков?",
        "Answer": "Стая",
        "AcceptableAnswers": "Стая"
    },
    {
        "Id": 117,
        "Text": "В какой стране находится город Токио?",
        "Answer": "Япония",
        "AcceptableAnswers": "Япония"
    },
    {
        "Id": 118,
        "Text": "Как называется наука о растениях?",
        "Answer": "Ботаника",
        "AcceptableAnswers": "Ботаника"
    },
    {
        "Id": 119,
        "Text": "В какой спортивной игре используется мяч и кольцо?",
        "Answer": "Баскетбол",
        "AcceptableAnswers": "Баскетбол"
    },
    {
        "Id": 120,
        "Text": "Как называется жидкость, текущая в венах?",
        "Answer": "Кровь",
        "AcceptableAnswers": "Кровь"
    },
    {
        "Id": 121,
        "Text": "Как называется столица Китая?",
        "Answer": "Пекин",
        "AcceptableAnswers": "Пекин"
    },
    {
        "Id": 122,
        "Text": "Сколько струн у классической гитары?",
        "Answer": "Шесть",
        "AcceptableAnswers": "Шесть"
    },
    {
        "Id": 123,
        "Text": "В каком месяце 28 или 29 дней?",
        "Answer": "Февраль",
        "AcceptableAnswers": "Февраль"
    },
    {
        "Id": 124,
        "Text": "Какой газ мы поглощаем при дыхании?",
        "Answer": "Кислород",
        "AcceptableAnswers": "Кислород"
    },
    {
        "Id": 125,
        "Text": "Как называется столица Испании?",
        "Answer": "Мадрид",
        "AcceptableAnswers": "Мадрид"
    },
    {
        "Id": 126,
        "Text": "Как называется самая маленькая птица?",
        "Answer": "Колибри",
        "AcceptableAnswers": "Колибри"
    },
    {
        "Id": 127,
        "Text": "С каким государством у России самая длинная граница?",
        "Answer": "Казахстан",
        "AcceptableAnswers": "Казахстан"
    },
    {
        "Id": 128,
        "Text": "Какой цвет у изумруда?",
        "Answer": "Зеленый",
        "AcceptableAnswers": "Зеленый"
    },
    {
        "Id": 129,
        "Text": "Как называется подземная железная дорога?",
        "Answer": "Метро",
        "AcceptableAnswers": "Метро"
    },
    {
        "Id": 130,
        "Text": "Что измеряют в амперах?",
        "Answer": "Сила тока",
        "AcceptableAnswers": "Сила тока"
    },
    {
        "Id": 131,
        "Text": "Как называется процесс превращения гусеницы в бабочку?",
        "Answer": "Метаморфоз",
        "AcceptableAnswers": "Метаморфоз"
    },
    {
        "Id": 132,
        "Text": "В каком виде спорта прославился Майкл Джордан?",
        "Answer": "Баскетбол",
        "AcceptableAnswers": "Баскетбол"
    },
    {
        "Id": 133,
        "Text": "Какое время года идет после весны?",
        "Answer": "Лето",
        "AcceptableAnswers": "Лето"
    },
    {
        "Id": 134,
        "Text": "Из чего делают стекло?",
        "Answer": "Песок",
        "AcceptableAnswers": "Песок"
    },
    {
        "Id": 135,
        "Text": "Какой континент самый холодный?",
        "Answer": "Антарктида",
        "AcceptableAnswers": "Антарктида"
    },
    {
        "Id": 136,
        "Text": "Как называется дом для пчел?",
        "Answer": "Улей",
        "AcceptableAnswers": "Улей"
    },
    {
        "Id": 137,
        "Text": "Какой орган используется для дыхания у рыб?",
        "Answer": "Жабры",
        "AcceptableAnswers": "Жабры"
    },
    {
        "Id": 138,
        "Text": "Какого цвета кровь у осьминога?",
        "Answer": "Синего",
        "AcceptableAnswers": "Синего"
    },
    {
        "Id": 139,
        "Text": "Как называется первый месяц года?",
        "Answer": "Январь",
        "AcceptableAnswers": "Январь"
    },
    {
        "Id": 140,
        "Text": "Сколько планет в Солнечной системе?",
        "Answer": "Восемь",
        "AcceptableAnswers": "Восемь"
    },
    {
        "Id": 141,
        "Text": "Как называется здание, где показывают фильмы?",
        "Answer": "Кинотеатр",
        "AcceptableAnswers": "Кинотеатр"
    },
    {
        "Id": 142,
        "Text": "Какое животное мычит?",
        "Answer": "Корова",
        "AcceptableAnswers": "Корова"
    },
    {
        "Id": 143,
        "Text": "Какой фрукт желтый и кислый?",
        "Answer": "Лимон",
        "AcceptableAnswers": "Лимон"
    },
    {
        "Id": 144,
        "Text": "Как называется столица Польши?",
        "Answer": "Варшава",
        "AcceptableAnswers": "Варшава"
    },
    {
        "Id": 145,
        "Text": "В какой стране находится пирамида Хеопса?",
        "Answer": "Египет",
        "AcceptableAnswers": "Египет"
    },
    {
        "Id": 146,
        "Text": "Как называется наука о животных?",
        "Answer": "Зоология",
        "AcceptableAnswers": "Зоология"
    },
    {
        "Id": 147,
        "Text": "Какой океан самый холодный?",
        "Answer": "Северный Ледовитый",
        "AcceptableAnswers": "Северный Ледовитый"
    },
    {
        "Id": 148,
        "Text": "Сколько дней в неделе?",
        "Answer": "Семь",
        "AcceptableAnswers": "Семь"
    },
    {
        "Id": 149,
        "Text": "Как называется верхняя одежда от дождя?",
        "Answer": "Дождевик",
        "AcceptableAnswers": "Дождевик"
    },
    {
        "Id": 150,
        "Text": "Какое дерево имеет белую кору?",
        "Answer": "Береза",
        "AcceptableAnswers": "Береза"
    },
    {
        "Id": 151,
        "Text": "Из какого молока делают сыр Рокфор?",
        "Answer": "Овечье",
        "AcceptableAnswers": "Овечье"
    },
    {
        "Id": 152,
        "Text": "Как называется столица Канады?",
        "Answer": "Оттава",
        "AcceptableAnswers": "Оттава"
    },
    {
        "Id": 153,
        "Text": "Назовите самый большой континент.",
        "Answer": "Евразия",
        "AcceptableAnswers": "Евразия"
    },
    {
        "Id": 154,
        "Text": "Какое число называют дюжиной?",
        "Answer": "Двенадцать",
        "AcceptableAnswers": "Двенадцать"
    },
    {
        "Id": 155,
        "Text": "Как называется искусство сложения бумаги?",
        "Answer": "Оригами",
        "AcceptableAnswers": "Оригами"
    },
    {
        "Id": 156,
        "Text": "В каком океане находится Марианская впадина?",
        "Answer": "Тихий",
        "AcceptableAnswers": "Тихий"
    },
    {
        "Id": 157,
        "Text": "Какой штат США самый большой по площади?",
        "Answer": "Аляска",
        "AcceptableAnswers": "Аляска"
    },
    {
        "Id": 158,
        "Text": "В каком городе находится Колизей?",
        "Answer": "Рим",
        "AcceptableAnswers": "Рим"
    },
    {
        "Id": 159,
        "Text": "Как называется линия, делящая Землю пополам?",
        "Answer": "Экватор",
        "AcceptableAnswers": "Экватор"
    },
    {
        "Id": 160,
        "Text": "Какое животное лает?",
        "Answer": "Собака",
        "AcceptableAnswers": "Собака"
    },
    {
        "Id": 161,
        "Text": "Как называется результат вычитания?",
        "Answer": "Разность",
        "AcceptableAnswers": "Разность"
    },
    {
        "Id": 162,
        "Text": "Как называется наука о строении тела?",
        "Answer": "Анатомия",
        "AcceptableAnswers": "Анатомия"
    },
    {
        "Id": 163,
        "Text": "Какой цветок считается символом любви?",
        "Answer": "Роза",
        "AcceptableAnswers": "Роза"
    },
    {
        "Id": 164,
        "Text": "В какой стране изобрели компас?",
        "Answer": "Китай",
        "AcceptableAnswers": "Китай"
    },
    {
        "Id": 165,
        "Text": "Какого цвета рубин?",
        "Answer": "Красный",
        "AcceptableAnswers": "Красный"
    },
    {
        "Id": 166,
        "Text": "Как называется первый день недели?",
        "Answer": "Понедельник",
        "AcceptableAnswers": "Понедельник"
    },
    {
        "Id": 167,
        "Text": "Сколько сантиметров в метре?",
        "Answer": "Сто",
        "AcceptableAnswers": "Сто"
    },
    {
        "Id": 168,
        "Text": "Какое насекомое делает мед?",
        "Answer": "Пчела",
        "AcceptableAnswers": "Пчела"
    },
    {
        "Id": 169,
        "Text": "Назовите столицу Великобритании.",
        "Answer": "Лондон",
        "AcceptableAnswers": "Лондон"
    },
    {
        "Id": 170,
        "Text": "Какой материк находится южнее всех?",
        "Answer": "Антарктида",
        "AcceptableAnswers": "Антарктида"
    },
    {
        "Id": 171,
        "Text": "В каком виде спорта используется клюшка и шайба?",
        "Answer": "Хоккей",
        "AcceptableAnswers": "Хоккей"
    },
    {
        "Id": 172,
        "Text": "Какой континент знаменит кенгуру?",
        "Answer": "Австралия",
        "AcceptableAnswers": "Австралия"
    },
    {
        "Id": 173,
        "Text": "Как называется подземная часть растения?",
        "Answer": "Корень",
        "AcceptableAnswers": "Корень"
    },
    {
        "Id": 174,
        "Text": "Какой химический элемент обозначается символом H?",
        "Answer": "Водород",
        "AcceptableAnswers": "Водород"
    },
    {
        "Id": 175,
        "Text": "Как называется самая высокая гора в Африке?",
        "Answer": "Килиманджаро",
        "AcceptableAnswers": "Килиманджаро"
    },
    {
        "Id": 176,
        "Text": "Какая валюта в Японии?",
        "Answer": "Иена",
        "AcceptableAnswers": "Иена"
    },
    {
        "Id": 177,
        "Text": "Как называется аппарат для разговора на расстоянии?",
        "Answer": "Телефон",
        "AcceptableAnswers": "Телефон"
    },
    {
        "Id": 178,
        "Text": "В какой стране находится Тадж-Махал?",
        "Answer": "Индия",
        "AcceptableAnswers": "Индия"
    },
    {
        "Id": 179,
        "Text": "Какая птица самая большая в мире?",
        "Answer": "Страус",
        "AcceptableAnswers": "Страус"
    },
    {
        "Id": 180,
        "Text": "Как называется природный спутник Земли?",
        "Answer": "Луна",
        "AcceptableAnswers": "Луна"
    },
    {
        "Id": 181,
        "Text": "Какой металл используется для изготовления термометров?",
        "Answer": "Ртуть",
        "AcceptableAnswers": "Ртуть"
    },
    {
        "Id": 182,
        "Text": "Как называется место, где скрещиваются две дороги?",
        "Answer": "Перекресток",
        "AcceptableAnswers": "Перекресток"
    },
    {
        "Id": 183,
        "Text": "Назовите столицу Индии.",
        "Answer": "Нью-Дели",
        "AcceptableAnswers": "Нью-Дели"
    },
    {
        "Id": 184,
        "Text": "Сколько миллиметров в сантиметре?",
        "Answer": "Десять",
        "AcceptableAnswers": "Десять"
    },
    {
        "Id": 185,
        "Text": "Как называется зимняя обувь для катания по льду?",
        "Answer": "Коньки",
        "AcceptableAnswers": "Коньки"
    },
    {
        "Id": 186,
        "Text": "Какой овощ заставляет нас плакать при резке?",
        "Answer": "Лук",
        "AcceptableAnswers": "Лук"
    },
    {
        "Id": 187,
        "Text": "В какой стране находится Пизанская башня?",
        "Answer": "Италия",
        "AcceptableAnswers": "Италия"
    },
    {
        "Id": 188,
        "Text": "Что строят бобры на реках?",
        "Answer": "Плотины",
        "AcceptableAnswers": "Плотины"
    },
    {
        "Id": 189,
        "Text": "Какой цвет у листьев летом?",
        "Answer": "Зеленый",
        "AcceptableAnswers": "Зеленый"
    },
    {
        "Id": 190,
        "Text": "Какой инструмент используется для черчения круга?",
        "Answer": "Циркуль",
        "AcceptableAnswers": "Циркуль"
    },
    {
        "Id": 191,
        "Text": "Назовите столицу Южной Кореи.",
        "Answer": "Сеул",
        "AcceptableAnswers": "Сеул"
    },
    {
        "Id": 192,
        "Text": "Какое море самое глубокое?",
        "Answer": "Филиппинское",
        "AcceptableAnswers": "Филиппинское"
    },
    {
        "Id": 193,
        "Text": "Из какой сказки слова: «Сим-сим, откройся»?",
        "Answer": "Али-Баба и сорок разбойников",
        "AcceptableAnswers": "Али-Баба и сорок разбойников"
    },
    {
        "Id": 194,
        "Text": "В каком городе находится Эйфелева башня?",
        "Answer": "Париж",
        "AcceptableAnswers": "Париж"
    },
    {
        "Id": 195,
        "Text": "Как называется прибор для измерения массы?",
        "Answer": "Весы",
        "AcceptableAnswers": "Весы"
    },
    {
        "Id": 196,
        "Text": "Какой злак используется для приготовления ризотто?",
        "Answer": "Рис",
        "AcceptableAnswers": "Рис"
    },
    {
        "Id": 197,
        "Text": "Как называется столица Финляндии?",
        "Answer": "Хельсинки",
        "AcceptableAnswers": "Хельсинки"
    },
    {
        "Id": 198,
        "Text": "В какой стране находится город Рио-де-Жанейро?",
        "Answer": "Бразилия",
        "AcceptableAnswers": "Бразилия"
    },
    {
        "Id": 199,
        "Text": "Сколько игроков в баскетбольной команде на площадке?",
        "Answer": "Пять",
        "AcceptableAnswers": "Пять"
    },
    {
        "Id": 200,
        "Text": "Как называется жилище птицы?",
        "Answer": "Гнездо",
        "AcceptableAnswers": "Гнездо"
    },
    {
        "Id": 201,
        "Text": "Какой цвет светофора означает «стоп»?",
        "Answer": "Красный",
        "AcceptableAnswers": "Красный"
    },
    {
        "Id": 202,
        "Text": "Какой цвет у сапфира?",
        "Answer": "Синий",
        "AcceptableAnswers": "Синий"
    },
    {
        "Id": 203,
        "Text": "Как называется столица Норвегии?",
        "Answer": "Осло",
        "AcceptableAnswers": "Осло"
    },
    {
        "Id": 204,
        "Text": "Как называется наука о космосе?",
        "Answer": "Астрономия",
        "AcceptableAnswers": "Астрономия"
    },
    {
        "Id": 205,
        "Text": "Назовите столицу Португалии.",
        "Answer": "Лиссабон",
        "AcceptableAnswers": "Лиссабон"
    },
    {
        "Id": 206,
        "Text": "Какое животное самое высокое?",
        "Answer": "Жираф",
        "AcceptableAnswers": "Жираф"
    },
    {
        "Id": 207,
        "Text": "Сколько зубов у взрослого человека?",
        "Answer": "32",
        "AcceptableAnswers": "32"
    },
    {
        "Id": 208,
        "Text": "Какая река самая длинная в Европе?",
        "Answer": "Волга",
        "AcceptableAnswers": "Волга"
    },
    {
        "Id": 209,
        "Text": "В какой стране родился Моцарт?",
        "Answer": "Австрия",
        "AcceptableAnswers": "Австрия"
    },
    {
        "Id": 210,
        "Text": "Как называется валюта в Великобритании?",
        "Answer": "Фунт",
        "AcceptableAnswers": "Фунт"
    },
    {
        "Id": 211,
        "Text": "Как называется столица Турции?",
        "Answer": "Анкара",
        "AcceptableAnswers": "Анкара"
    },
    {
        "Id": 212,
        "Text": "Какой овощ главный в борще?",
        "Answer": "Свекла",
        "AcceptableAnswers": "Свекла"
    },
    {
        "Id": 213,
        "Text": "Какой праздник отмечают 31 декабря?",
        "Answer": "Новый год",
        "AcceptableAnswers": "Новый год"
    },
    {
        "Id": 214,
        "Text": "Как называется столица Чехии?",
        "Answer": "Прага",
        "AcceptableAnswers": "Прага"
    },
    {
        "Id": 215,
        "Text": "Какое животное ест эвкалипт?",
        "Answer": "Коала",
        "AcceptableAnswers": "Коала"
    },
    {
        "Id": 216,
        "Text": "Сколько сторон у шестиугольника?",
        "Answer": "Шесть",
        "AcceptableAnswers": "Шесть"
    },
    {
        "Id": 217,
        "Text": "Какая гора самая высокая в России?",
        "Answer": "Эльбрус",
        "AcceptableAnswers": "Эльбрус"
    },
    {
        "Id": 218,
        "Text": "В каком виде спорта выступал Пеле?",
        "Answer": "Футбол",
        "AcceptableAnswers": "Футбол"
    },
    {
        "Id": 219,
        "Text": "Как называется прибор для осмотра звезд?",
        "Answer": "Телескоп",
        "AcceptableAnswers": "Телескоп"
    },
    {
        "Id": 220,
        "Text": "Какой месяц последний в году?",
        "Answer": "Декабрь",
        "AcceptableAnswers": "Декабрь"
    },
    {
        "Id": 221,
        "Text": "Назовите столицу Греции.",
        "Answer": "Афины",
        "AcceptableAnswers": "Афины"
    },
    {
        "Id": 222,
        "Text": "Что измеряют в герцах?",
        "Answer": "Частоту",
        "AcceptableAnswers": "Частоту"
    },
    {
        "Id": 223,
        "Text": "Какая птица лечит деревья?",
        "Answer": "Дятел",
        "AcceptableAnswers": "Дятел"
    },
    {
        "Id": 224,
        "Text": "Как называется здание для автомобилей?",
        "Answer": "Гараж",
        "AcceptableAnswers": "Гараж"
    },
    {
        "Id": 225,
        "Text": "Назовите столицу Кубы.",
        "Answer": "Гавана",
        "AcceptableAnswers": "Гавана"
    },
    {
        "Id": 226,
        "Text": "Как называется наука о Земле?",
        "Answer": "География",
        "AcceptableAnswers": "География"
    },
    {
        "Id": 227,
        "Text": "Какой цвет у снега?",
        "Answer": "Белый",
        "AcceptableAnswers": "Белый"
    },
    {
        "Id": 228,
        "Text": "Как называется период из 100 лет?",
        "Answer": "Век",
        "AcceptableAnswers": "Век"
    },
    {
        "Id": 229,
        "Text": "В каком городе находится Красная площадь?",
        "Answer": "Москва",
        "AcceptableAnswers": "Москва"
    },
    {
        "Id": 230,
        "Text": "Назовите столицу Швеции.",
        "Answer": "Стокгольм",
        "AcceptableAnswers": "Стокгольм"
    },
    {
        "Id": 231,
        "Text": "Что растет на дубе?",
        "Answer": "Желуди",
        "AcceptableAnswers": "Желуди"
    },
    {
        "Id": 232,
        "Text": "Какая единица измерения громкости звука?",
        "Answer": "Децибел",
        "AcceptableAnswers": "Децибел"
    },
    {
        "Id": 233,
        "Text": "В какой стране находится город Сидней?",
        "Answer": "Австралия",
        "AcceptableAnswers": "Австралия"
    },
    {
        "Id": 234,
        "Text": "Какая страна является родиной Олимпийских игр?",
        "Answer": "Греция",
        "AcceptableAnswers": "Греция"
    },
    {
        "Id": 235,
        "Text": "Как называется утренний прием пищи?",
        "Answer": "Завтрак",
        "AcceptableAnswers": "Завтрак"
    },
    {
        "Id": 236,
        "Text": "Какой материк омывается четырьмя океанами?",
        "Answer": "Евразия",
        "AcceptableAnswers": "Евразия"
    },
    {
        "Id": 237,
        "Text": "В какой стране находится город Барселона?",
        "Answer": "Испания",
        "AcceptableAnswers": "Испания"
    },
    {
        "Id": 238,
        "Text": "Как называется первый летний месяц?",
        "Answer": "Июнь",
        "AcceptableAnswers": "Июнь"
    },
    {
        "Id": 239,
        "Text": "Какая страна знаменита пиццей?",
        "Answer": "Италия",
        "AcceptableAnswers": "Италия"
    },
    {
        "Id": 240,
        "Text": "Сколько месяцев в году?",
        "Answer": "Двенадцать",
        "AcceptableAnswers": "Двенадцать"
    },
    {
        "Id": 241,
        "Text": "Как называется жилище муравьев?",
        "Answer": "Муравейник",
        "AcceptableAnswers": "Муравейник"
    },
    {
        "Id": 242,
        "Text": "Назовите столицу Таиланда.",
        "Answer": "Бангкок",
        "AcceptableAnswers": "Бангкок"
    },
    {
        "Id": 243,
        "Text": "Какое природное явление сопровождается громом?",
        "Answer": "Молния",
        "AcceptableAnswers": "Молния"
    },
    {
        "Id": 244,
        "Text": "Как называется наука о словах?",
        "Answer": "Лингвистика",
        "AcceptableAnswers": "Лингвистика"
    },
    {
        "Id": 245,
        "Text": "Назовите столицу Ирландии.",
        "Answer": "Дублин",
        "AcceptableAnswers": "Дублин"
    },
    {
        "Id": 246,
        "Text": "Какое животное считается царем зверей?",
        "Answer": "Лев",
        "AcceptableAnswers": "Лев"
    },
    {
        "Id": 247,
        "Text": "Какой океан омывает западное побережье США?",
        "Answer": "Тихий",
        "AcceptableAnswers": "Тихий"
    },
    {
        "Id": 248,
        "Text": "Как называется твердое состояние воды?",
        "Answer": "Лед",
        "AcceptableAnswers": "Лед"
    },
    {
        "Id": 249,
        "Text": "Какой инструмент у дровосека?",
        "Answer": "Топор",
        "AcceptableAnswers": "Топор"
    },
    {
        "Id": 250,
        "Text": "Как называется столица Мексики?",
        "Answer": "Мехико",
        "AcceptableAnswers": "Мехико"
    },
    {
        "Id": 251,
        "Text": "Какая река течет в Египте?",
        "Answer": "Нил",
        "AcceptableAnswers": "Нил"
    },
    {
        "Id": 252,
        "Text": "Что находится в центре Земли?",
        "Answer": "Ядро",
        "AcceptableAnswers": "Ядро"
    },
    {
        "Id": 253,
        "Text": "Назовите столицу Дании.",
        "Answer": "Копенгаген",
        "AcceptableAnswers": "Копенгаген"
    },
    {
        "Id": 254,
        "Text": "Как называется плод яблони?",
        "Answer": "Яблоко",
        "AcceptableAnswers": "Яблоко"
    },
    {
        "Id": 255,
        "Text": "Как называется врач, лечащий зубы?",
        "Answer": "Дантист",
        "AcceptableAnswers": "Дантист"
    },
    {
        "Id": 256,
        "Text": "Сколько дней в обычном феврале?",
        "Answer": "28",
        "AcceptableAnswers": "28"
    },
    {
        "Id": 257,
        "Text": "Какой металл используют для проводов?",
        "Answer": "Медь",
        "AcceptableAnswers": "Медь"
    },
    {
        "Id": 258,
        "Text": "В каком месяце отмечают 8 Марта?",
        "Answer": "Март",
        "AcceptableAnswers": "Март"
    },
    {
        "Id": 259,
        "Text": "Назовите столицу Австрии.",
        "Answer": "Вена",
        "AcceptableAnswers": "Вена"
    },
    {
        "Id": 260,
        "Text": "Как называется отверстие в вулкане?",
        "Answer": "Кратер",
        "AcceptableAnswers": "Кратер"
    },
    {
        "Id": 261,
        "Text": "Сколько игроков в волейбольной команде на площадке?",
        "Answer": "Шесть",
        "AcceptableAnswers": "Шесть"
    },
    {
        "Id": 262,
        "Text": "Назовите столицу Швейцарии.",
        "Answer": "Берн",
        "AcceptableAnswers": "Берн"
    },
    {
        "Id": 263,
        "Text": "Что пчелы собирают с цветов?",
        "Answer": "Нектар",
        "AcceptableAnswers": "Нектар"
    },
    {
        "Id": 264,
        "Text": "Какой овощ бывает сладким и болгарским?",
        "Answer": "Перец",
        "AcceptableAnswers": "Перец"
    },
    {
        "Id": 265,
        "Text": "Как называется столица Бельгии?",
        "Answer": "Брюссель",
        "AcceptableAnswers": "Брюссель"
    },
    {
        "Id": 266,
        "Text": "Какой материк наименьший?",
        "Answer": "Австралия",
        "AcceptableAnswers": "Австралия"
    },
    {
        "Id": 267,
        "Text": "Как называется место для стоянки кораблей?",
        "Answer": "Порт",
        "AcceptableAnswers": "Порт"
    },
    {
        "Id": 268,
        "Text": "Что находится внутри ореха?",
        "Answer": "Ядро",
        "AcceptableAnswers": "Ядро"
    },
    {
        "Id": 269,
        "Text": "Назовите столицу Нидерландов.",
        "Answer": "Амстердам",
        "AcceptableAnswers": "Амстердам"
    },
    {
        "Id": 270,
        "Text": "Какое число называют чертовой дюжиной?",
        "Answer": "Тринадцать",
        "AcceptableAnswers": "Тринадцать"
    },
    {
        "Id": 271,
        "Text": "Какой континент самый жаркий?",
        "Answer": "Африка",
        "AcceptableAnswers": "Африка"
    },
    {
        "Id": 272,
        "Text": "Как называется столица Аргентины?",
        "Answer": "Буэнос-Айрес",
        "AcceptableAnswers": "Буэнос-Айрес"
    },
    {
        "Id": 273,
        "Text": "Какая птица говорит «кар»?",
        "Answer": "Ворона",
        "AcceptableAnswers": "Ворона"
    },
    {
        "Id": 274,
        "Text": "Из чего делают вино?",
        "Answer": "Виноград",
        "AcceptableAnswers": "Виноград"
    },
    {
        "Id": 275,
        "Text": "Назовите столицу Венгрии.",
        "Answer": "Будапешт",
        "AcceptableAnswers": "Будапешт"
    },
    {
        "Id": 276,
        "Text": "Как называется человек, который водит самолет?",
        "Answer": "Пилот",
        "AcceptableAnswers": "Пилот"
    },
    {
        "Id": 277,
        "Text": "Как называется наука о числах?",
        "Answer": "Математика",
        "AcceptableAnswers": "Математика"
    },
    {
        "Id": 278,
        "Text": "Назовите столицу Чили.",
        "Answer": "Сантьяго",
        "AcceptableAnswers": "Сантьяго"
    },
    {
        "Id": 279,
        "Text": "Что мы видим на небе ночью?",
        "Answer": "Звезды",
        "AcceptableAnswers": "Звезды"
    },
    {
        "Id": 280,
        "Text": "Какое дерево считается символом России?",
        "Answer": "Береза",
        "AcceptableAnswers": "Береза"
    },
    {
        "Id": 281,
        "Text": "Назовите столицу Израиля.",
        "Answer": "Иерусалим",
        "AcceptableAnswers": "Иерусалим"
    },
    {
        "Id": 282,
        "Text": "В какой стране находится город Мюнхен?",
        "Answer": "Германия",
        "AcceptableAnswers": "Германия"
    },
    {
        "Id": 283,
        "Text": "Какое животное покрыто панцирем и медленно ходит?",
        "Answer": "Черепаха",
        "AcceptableAnswers": "Черепаха"
    },
    {
        "Id": 284,
        "Text": "Как называется столица Румынии?",
        "Answer": "Бухарест",
        "AcceptableAnswers": "Бухарест"
    },
    {
        "Id": 285,
        "Text": "Какой металл используется для производства фольги?",
        "Answer": "Алюминий",
        "AcceptableAnswers": "Алюминий"
    },
    {
        "Id": 286,
        "Text": "В каком городе находится Статуя Иисуса Искупителя?",
        "Answer": "Рио-де-Жанейро",
        "AcceptableAnswers": "Рио-де-Жанейро"
    },
    {
        "Id": 287,
        "Text": "Назовите столицу Чехии.",
        "Answer": "Прага",
        "AcceptableAnswers": "Прага"
    },
    {
        "Id": 288,
        "Text": "Как называется детеныш коровы?",
        "Answer": "Теленок",
        "AcceptableAnswers": "Теленок"
    },
    {
        "Id": 289,
        "Text": "Назовите столицу Перу.",
        "Answer": "Лима",
        "AcceptableAnswers": "Лима"
    },
    {
        "Id": 290,
        "Text": "Какое растение используют для производства сахара?",
        "Answer": "Свекла",
        "AcceptableAnswers": "Свекла"
    },
    {
        "Id": 291,
        "Text": "Назовите столицу Венесуэлы.",
        "Answer": "Каракас",
        "AcceptableAnswers": "Каракас"
    },
    {
        "Id": 292,
        "Text": "Как называется прибор для измерения атмосферного давления?",
        "Answer": "Барометр",
        "AcceptableAnswers": "Барометр"
    },
    {
        "Id": 293,
        "Text": "Какой вид спорта ассоциируется с Уимблдоном?",
        "Answer": "Теннис",
        "AcceptableAnswers": "Теннис"
    },
    {
        "Id": 294,
        "Text": "Какое животное оставляет шерсть на клубок?",
        "Answer": "Овца",
        "AcceptableAnswers": "Овца"
    },
    {
        "Id": 295,
        "Text": "Назовите столицу Египта.",
        "Answer": "Каир",
        "AcceptableAnswers": "Каир"
    },
    {
        "Id": 296,
        "Text": "Какая часть компьютера используется для набора текста?",
        "Answer": "Клавиатура",
        "AcceptableAnswers": "Клавиатура"
    },
    {
        "Id": 297,
        "Text": "Какое дерево имеет иголки вместо листьев?",
        "Answer": "Сосна",
        "AcceptableAnswers": "Сосна"
    },
    {
        "Id": 298,
        "Text": "Назовите столицу Афганистана.",
        "Answer": "Кабул",
        "AcceptableAnswers": "Кабул"
    },
    {
        "Id": 299,
        "Text": "Какой континент называется «новым светом»?",
        "Answer": "Америка",
        "AcceptableAnswers": "Америка"
    },
    {
        "Id": 300,
        "Text": "Как называется столица Ирака?",
        "Answer": "Багдад",
        "AcceptableAnswers": "Багдад"
    },
    {
        "Id": 301,
        "Text": "Какой месяц следует после августа?",
        "Answer": "Сентябрь",
        "AcceptableAnswers": "Сентябрь"
    }
]